azure/iot/deviceprovisioning/__init__.py
azure/iot/deviceprovisioning/_api_version.py
azure/iot/deviceprovisioning/_auth.py
azure/iot/deviceprovisioning/_client.py
azure/iot/deviceprovisioning/_configuration.py
azure/iot/deviceprovisioning/_patch.py
azure/iot/deviceprovisioning/_serialization.py
azure/iot/deviceprovisioning/_vendor.py
azure/iot/deviceprovisioning/_version.py
azure/iot/deviceprovisioning/py.typed
azure/iot/deviceprovisioning/aio/__init__.py
azure/iot/deviceprovisioning/aio/_client.py
azure/iot/deviceprovisioning/aio/_configuration.py
azure/iot/deviceprovisioning/aio/_patch.py
azure/iot/deviceprovisioning/aio/operations/__init__.py
azure/iot/deviceprovisioning/aio/operations/_operations.py
azure/iot/deviceprovisioning/aio/operations/_patch.py
azure/iot/deviceprovisioning/operations/__init__.py
azure/iot/deviceprovisioning/operations/_operations.py
azure/iot/deviceprovisioning/operations/_patch.py
azure_iot_deviceprovisioning-1.0.0b1.dist-info/LICENSE
azure_iot_deviceprovisioning-1.0.0b1.dist-info/METADATA
azure_iot_deviceprovisioning-1.0.0b1.dist-info/WHEEL
azure_iot_deviceprovisioning-1.0.0b1.dist-info/top_level.txt
azure_iot_deviceprovisioning-1.0.0b1.dist-info/RECORD
